uv_jupyter_kernel.py
uv_jupyter_kernel-0.2.4.dist-info/METADATA
uv_jupyter_kernel-0.2.4.dist-info/WHEEL
uv_jupyter_kernel-0.2.4.dist-info/entry_points.txt
uv_jupyter_kernel-0.2.4.dist-info/licenses/LICENSE
uv_jupyter_kernel-0.2.4.dist-info/RECORD
