Metadata-Version: 2.4
Name: uv-jupyter-kernel
Version: 0.2.4
Summary: Add your description here
License-File: LICENSE
Requires-Python: >=3.13
